flask_azure_storage.py
setup.py
Flask_Azure_Storage.egg-info/PKG-INFO
Flask_Azure_Storage.egg-info/SOURCES.txt
Flask_Azure_Storage.egg-info/dependency_links.txt
Flask_Azure_Storage.egg-info/not-zip-safe
Flask_Azure_Storage.egg-info/requires.txt
Flask_Azure_Storage.egg-info/top_level.txt