Metadata-Version: 1.1
Name: Flask-Azure-Storage
Version: 0.1
Summary: Flask extension that provides integration with Azure Storage
Home-page: https://github.com/alejoar/Flask-Azure-Storage
Author: Alejo Arias
Author-email: alejoar@gmail.com
License: MIT
Platform: any
Classifier: Environment :: Web Environment
Classifier: Intended Audience :: Developers
Classifier: License :: OSI Approved :: MIT License
Classifier: Operating System :: OS Independent
Classifier: Programming Language :: Python
Classifier: Topic :: Internet :: WWW/HTTP :: Dynamic Content
Classifier: Topic :: Software Development :: Libraries :: Python Modules
